{
    "deutsch": {
        "klavier": {
            "definition": "piano",
            "next_review": "2025-08-16 14:57:49"
        },
        "kinderwagen": {
            "definition": "karotsaki",
            "next_review": "2025-08-16 14:57:58"
        },
        "handy": {
            "definition": "kinito",
            "next_review": "2025-08-16 14:57:32"
        },
        "katze": {
            "definition": "gata",
            "next_review": "2025-08-11 15:02:45"
        },
        "einrichtung": {
            "definition": "epipla",
            "next_review": "2025-08-16 14:57:54"
        }
    }
}